Workbook

Sheet Report
A1: Vehicle Status | approval summary
A3: AAOS-first reuse pilot / DAR-SDV-VS-001 v1.2 / recovery approval requested
A4: Inputs changes resources. Report updates automatically. Business Case adds optional costs and effort payback.
A6: REDUCED DEMO / WEEK | C6: FULL PILOT / WEEK | F6: WITH RESERVE / WEEK
A7: =IFERROR(IF(Plan!I20="","BLOCKED",Plan!I13),"") -> 8 | C7: =IFERROR(IF(Plan!I20="","BLOCKED",Plan!I17),"") -> 18 | F7: =IFERROR(IF(Plan!I20="","BLOCKED",Plan!I17+Inputs!C22),"") -> 20
A10: =IFERROR(IF(Plan!I20="","Forecast blocked. Correct Inputs / Plan first.","Selected team: "&Inputs!C5&" developers ("&Inputs!C7&" experienced + "&Inputs!C6&" junior). Estimated delivery work: "&TEXT((Plan!C20+Plan!D20)*Inputs!C24,"0")&" hours, including review and tests. This is planned work, not completed work."),"") -> Selected team: 2 developers (1 experienced + 1 junior). Estimated delivery work: 828 hours, including review and tests. This is planned work, not completed work.
A13: FORECAST CHECKPOINTS
A14: Checkpoint | C14: End week | D14: Finish date* | F14: Target week | G14: Variance | H14: Schedule
A15: Review / Gate A | C15: =IFERROR(IF(Plan!I20="","",Plan!I9),"") -> 2 | D15: =IFERROR(IF(OR(C15="",Inputs!C19=""),"",Inputs!C19+ROUNDUP(C15*Inputs!C25,0)-1),"") | F15: - | G15: - | H15: Forecast
A16: Shared rules / Gate B | C16: =IFERROR(IF(Plan!I20="","",Plan!I11),"") -> 5 | D16: =IFERROR(IF(OR(C16="",Inputs!C19=""),"",Inputs!C19+ROUNDUP(C16*Inputs!C25,0)-1),"") | F16: - | G16: - | H16: Forecast
A17: Reduced demo | C17: =IFERROR(IF(Plan!I20="","",Plan!I13),"") -> 8 | D17: =IFERROR(IF(OR(C17="",Inputs!C19=""),"",Inputs!C19+ROUNDUP(C17*Inputs!C25,0)-1),"") | F17: =IFERROR(Inputs!C20,"") -> 8 | G17: =IFERROR(IF(C17="","",C17-F17),"") -> 0 | H17: =IFERROR(IF(C17="","BLOCKED",IF(C17>F17,"LATE","WITHIN")),"") -> WITHIN
A18: Full pilot / Gate C | C18: =IFERROR(IF(Plan!I20="","",Plan!I17),"") -> 18 | D18: =IFERROR(IF(OR(C18="",Inputs!C19=""),"",Inputs!C19+ROUNDUP(C18*Inputs!C25,0)-1),"") | F18: =IFERROR(Inputs!C21,"") -> 18 | G18: =IFERROR(IF(C18="","",C18-F18),"") -> 0 | H18: =IFERROR(IF(C18="","BLOCKED",IF(C18>F18,"LATE","WITHIN")),"") -> WITHIN
A19: With reserve | C19: =IFERROR(IF(Plan!I20="","",Plan!I17+Inputs!C22),"") -> 20 | D19: =IFERROR(IF(OR(C19="",Inputs!C19=""),"",Inputs!C19+ROUNDUP(C19*Inputs!C25,0)-1),"") | F19: - | G19: - | H19: Forecast
A21: SCOPE AND DECISION
A22: Reduced demo | C22: One mapping -> shared rules -> first backend connection -> receiver receipt. No full-reuse or completed crash-recovery claim. Remote settings remain off.
A24: Full pilot | C24: Two mappings and connection methods; restart-safe buffering; authorized reporting settings; six test groups; next-platform design only. Not production approval.
A27: Allocated hours | C27: =IFERROR(IF(Plan!I20="","",Plan!I17*Inputs!C31),"") -> 1440 | F27: =IFERROR(IF(Plan!I20="","",(Plan!I17+Inputs!C22)*Inputs!C31),"") -> 1600
A29: =IFERROR(IF(Plan!I20="","Decision: correct blocked assumptions first.","Approve recovery only: "&TEXT(Plan!I9,"0.0")&" elapsed weeks and "&TEXT(Plan!I9*Inputs!C31,"0")&" allocated hours. "&IF(ISNUMBER('Business Case'!C16),"Estimated cost: "&TEXT('Business Case'!C16,"#,##0.00")&" "&'Business Case'!C5&". ","Money cap not set; enter rates/costs in Business Case. ")&"Re-estimate and confirm a consuming team at Gate A before funding the build."),"") -> Approve recovery only: 2.0 elapsed weeks and 160 allocated hours. Money cap not set; enter rates/costs in Business Case. Re-estimate and confirm a consuming team at Gate A before funding the build.
A32: Forecast only, not approval or passed tests. *Dates stay blank until Inputs!C19 is set. Calendar weeks are approximate. Benefits remain unproven; use Business Case for explicit assumptions, not claimed savings.
A35: Model check | C35: =IFERROR(IF(OR(Inputs!C32<>"OK",COUNT(Plan!I9:I17)<>9,COUNTIF(Plan!T9:T17,"BLOCKED")>0),"BLOCKED - review Inputs / Plan",IF(ABS(Scenarios!F9-Plan!I17)>0.000001,"ERROR - scenario mismatch","OK - formulas consistent; estimates require approval")),"") -> OK - formulas consistent; estimates require approval

Sheet Inputs
A1: Change the team, not the report
A3: Start here: C5 = total developers; C6 = juniors. Blue inputs change the forecast, not the selected idea.
A4: 1 TEAM
A5: Total developers | C5: 2 | E5: Changing 2 to 3 adds one experienced developer unless the junior count also changes.
A6: Intern / fresher count | C6: 1 | E6: Must be smaller than total developers. At least one experienced developer is required.
A7: Experienced developer count | C7: =IFERROR(C5-C6,"") -> 1 | E7: Total minus intern/fresher count. Assumes suitable AAOS/core skills.
A8: Paid hours per person / week | C8: 40 | E8: Nominal time; not all time becomes accepted delivery work.
A9: Experienced allocation | C9: 1 | E9: Share of working time assigned to this project.
A10: Junior allocation | C10: 1 | E10: Set below 100% for part-time internship or other assignments.
A11: 2 USABLE CAPACITY
A12: Experienced usable time before mentoring | C12: 0.85 | E12: Planning assumption: 85% of allocated time, before mentoring. Review after recovery; not a productivity benchmark.
A13: Junior accepted work rate, after recovery | C13: 0.6 | E13: 60% of allocated time; includes tests and evidence accepted after review.
A14: Junior accepted work rate, during recovery | C14: 0.3 | E14: Lower rate applies to the whole recovery phase, not a fixed number of weeks.
A15: Mentoring hours per allocated junior / week | C15: 6 | E15: Deducted once from the experienced pool; ordinary PR review stays inside work estimates.
A16: Maximum experienced contributors per phase | C16: 2 | E16: Caps useful parallel work. More staff do not automatically remove sequence or review limits.
A17: Maximum junior contributors per phase | C17: 2 | E17: Caps parallel support work. These contributor caps are proposed controls.
A18: 3 CALENDAR AND FORECAST
A19: Planning start date | E19: Leave blank until an approved start is agreed. Weeks still calculate; dates remain blank.
A20: Desired reduced-demo week | C20: 8 | E20: A comparison target, not a formula override or promise.
A21: Desired full-MVP week | C21: 18 | E21: A comparison target, not a formula override or promise.
A22: Sponsor-controlled reserve (weeks) | C22: 2 | E22: Added after the base forecast. Does not buy extra features.
A23: Schedule rounding step (weeks) | C23: 0.5 | E23: Rounds each phase upward. Use 0.5 or 1 week.
A24: Work estimate multiplier | C24: 1 | E24: 1.00 = source workload. 1.20 models 20% more work; does not change scope.
A25: Calendar days per elapsed week | C25: 7 | E25: Calendar dates are approximate elapsed-week dates, not a holiday-aware workday schedule.
A26: 4 CALCULATED CAPACITY
A27: Experienced pool: delivery hours / week | C27: =IFERROR(MAX(0,C7*C8*C9*C12-C6*C10*C15),"") -> 28 | E27: Before the per-phase contributor and senior-critical caps.
A28: Experienced: delivery hours per person | C28: =IFERROR(IF(C7>0,C27/C7,0),"") -> 28 | E28: Mentoring is shared across the experienced pool.
A29: Junior: hours per person after recovery | C29: =IFERROR(C8*C10*C13,"") -> 24 | E29: Used for phases P2-P9.
A30: Junior: hours per person during recovery | C30: =IFERROR(C8*C10*C14,"") -> 12 | E30: Used for phase P1 only.
A31: Nominal allocated team hours / week | C31: =IFERROR(C8*(C7*C9+C6*C10),"") -> 80 | E31: Staffed/allocated hours, not accepted work. Used for the staffing envelope.
A32: Input validation | C32: =IFERROR(IF(OR(NOT(ISNUMBER(C5)),NOT(ISNUMBER(C6)),NOT(ISNUMBER(C8)),NOT(ISNUMBER(C9)),NOT(ISNUMBER(C10)),NOT(ISNUMBER(C12)),NOT(ISNUMBER(C13)),NOT(ISNUMBER(C14)),NOT(ISNUMBER(C15)),NOT(ISNUMBER(C16)),NOT(ISNUMBER(C17)),NOT(ISNUMBER(C20)),NOT(ISNUMBER(C21)),NOT(ISNUMBER(C22)),NOT(ISNUMBER(C23)),NOT(ISNUMBER(C24)),NOT(ISNUMBER(C25)),C5<1,C5<>INT(C5),C6<0,C6<>INT(C6),C6>=C5,C8<=0,C9<=0,C9>1,C10<0,C10>1,C12<=0,C12>1,C13<0,C13>1,C14<0,C14>1,C15<0,C16<1,C16<>INT(C16),C17<0,C17<>INT(C17),AND(C19<>"",OR(NOT(ISNUMBER(C19)),C19<1,C19<>INT(C19))),C20<=0,C21<C20,C22<0,AND(C23<>0.5,C23<>1),C24<=0,C25<>7,C27<=0),"BLOCKED","OK"),"BLOCKED") -> OK | E32: BLOCKED means invalid or missing capacity/estimate inputs. An unset start date does not block week forecasts.
A34: No overtime, new production backend, independent security reviewer or completed AAOS SDV runtime port is assumed. Role changes alter the forecast, not the approved scope.

Sheet Plan
A1: Delivery plan | agreed scope, variable team
A3: Change blue estimates only after review. Phases run in order; limited parallel work is allowed within a phase.
A5: Forecast only. Pass evidence must be reviewed at the gate; a calculated finish date never means that a test passed. Expert = experienced developer. Support = work a junior can do under review.
A8: ID | B8: Phase | C8: Expert-only work (h) | D8: Support work (h) | E8: Minimum weeks | F8: Expert lead slots | G8: Waiting weeks | H8: Duration weeks | I8: Finish week | J8: Finish date | K8: Checkpoint | L8: Required evidence | N8: Junior pool h/w | O8: Expert critical h/w | P8: Expert total h/w | Q8: Combined h/w | R8: Raw duration | S8: Start offset weeks | T8: Phase input check
A9: P1 | B9: Review current AAOS prototype | C9: 56 | D9: 24 | E9: 2 | F9: 1 | G9: 0 | H9: =IFERROR(IF(NOT(ISNUMBER(R9)),"",ROUNDUP(R9/Inputs!$C$23,0)*Inputs!$C$23),"") -> 2 | I9: =IFERROR(IF(OR(NOT(ISNUMBER(H9)),NOT(ISNUMBER(S9))),"",S9+H9),"") -> 2 | J9: =IFERROR(IF(OR(I9="",Inputs!$C$19=""),"",Inputs!$C$19+ROUNDUP(I9*Inputs!$C$25,0)-1),"") | K9: Gate A | L9: Reproduce build and access; identify dependencies, consumer, risks and revised estimate. | N9: =IFERROR(MIN(Inputs!$C$6,Inputs!$C$17)*Inputs!$C$30,"") -> 12 | O9: =IFERROR(MIN(Inputs!$C$7,Inputs!$C$16,F9)*Inputs!$C$28,"") -> 28 | P9: =IFERROR(MIN(Inputs!$C$7,Inputs!$C$16)*Inputs!$C$28,"") -> 28 | Q9: =IFERROR(N9+P9,"") -> 40 | R9: =IFERROR(IF(OR(Inputs!$C$32<>"OK",T9<>"OK"),"",MAX(E9,C9*Inputs!$C$24/O9,(C9+D9)*Inputs!$C$24/Q9)),"") -> 2 | S9: =IFERROR(IF(OR(Inputs!$C$32<>"OK",T9<>"OK"),"",G9),"") -> 0 | T9: =IFERROR(IF(OR(COUNT(C9:G9)<>5,C9<0,D9<0,E9<0,F9<1,F9<>INT(F9),G9<0),"BLOCKED","OK"),"BLOCKED") -> OK
A10: P2 | B10: Define common reporting rules | C10: 56 | D10: 48 | E10: 1 | F10: 2 | G10: 0 | H10: =IFERROR(IF(NOT(ISNUMBER(R10)),"",ROUNDUP(R10/Inputs!$C$23,0)*Inputs!$C$23),"") -> 2 | I10: =IFERROR(IF(OR(NOT(ISNUMBER(H10)),NOT(ISNUMBER(S10))),"",S10+H10),"") -> 4 | J10: =IFERROR(IF(OR(I10="",Inputs!$C$19=""),"",Inputs!$C$19+ROUNDUP(I10*Inputs!$C$25,0)-1),"") | K10: Core foundation | L10: Agree data meanings, reporting triggers and connection boundaries; prepare repeatable inputs. | N10: =IFERROR(MIN(Inputs!$C$6,Inputs!$C$17)*Inputs!$C$29,"") -> 24 | O10: =IFERROR(MIN(Inputs!$C$7,Inputs!$C$16,F10)*Inputs!$C$28,"") -> 28 | P10: =IFERROR(MIN(Inputs!$C$7,Inputs!$C$16)*Inputs!$C$28,"") -> 28 | Q10: =IFERROR(N10+P10,"") -> 52 | R10: =IFERROR(IF(OR(Inputs!$C$32<>"OK",T10<>"OK"),"",MAX(E10,C10*Inputs!$C$24/O10,(C10+D10)*Inputs!$C$24/Q10)),"") -> 2 | S10: =IFERROR(IF(OR(Inputs!$C$32<>"OK",T10<>"OK",I9=""),"",I9+G10),"") -> 2 | T10: =IFERROR(IF(OR(COUNT(C10:G10)<>5,C10<0,D10<0,E10<0,F10<1,F10<>INT(F10),G10<0),"BLOCKED","OK"),"BLOCKED") -> OK
A11: P3 | B11: Verify the shared rules | C11: 28 | D11: 24 | E11: 1 | F11: 1 | G11: 0 | H11: =IFERROR(IF(NOT(ISNUMBER(R11)),"",ROUNDUP(R11/Inputs!$C$23,0)*Inputs!$C$23),"") -> 1 | I11: =IFERROR(IF(OR(NOT(ISNUMBER(H11)),NOT(ISNUMBER(S11))),"",S11+H11),"") -> 5 | J11: =IFERROR(IF(OR(I11="",Inputs!$C$19=""),"",Inputs!$C$19+ROUNDUP(I11*Inputs!$C$25,0)-1),"") | K11: Gate B | L11: S1-S2 pass; the shared rules build without Android or backend-specific code. | N11: =IFERROR(MIN(Inputs!$C$6,Inputs!$C$17)*Inputs!$C$29,"") -> 24 | O11: =IFERROR(MIN(Inputs!$C$7,Inputs!$C$16,F11)*Inputs!$C$28,"") -> 28 | P11: =IFERROR(MIN(Inputs!$C$7,Inputs!$C$16)*Inputs!$C$28,"") -> 28 | Q11: =IFERROR(N11+P11,"") -> 52 | R11: =IFERROR(IF(OR(Inputs!$C$32<>"OK",T11<>"OK"),"",MAX(E11,C11*Inputs!$C$24/O11,(C11+D11)*Inputs!$C$24/Q11)),"") -> 1 | S11: =IFERROR(IF(OR(Inputs!$C$32<>"OK",T11<>"OK",I10=""),"",I10+G11),"") -> 4 | T11: =IFERROR(IF(OR(COUNT(C11:G11)<>5,C11<0,D11<0,E11<0,F11<1,F11<>INT(F11),G11<0),"BLOCKED","OK"),"BLOCKED") -> OK
A12: P4 | B12: Connect AAOS vehicle data | C12: 28 | D12: 24 | E12: 1 | F12: 1 | G12: 0 | H12: =IFERROR(IF(NOT(ISNUMBER(R12)),"",ROUNDUP(R12/Inputs!$C$23,0)*Inputs!$C$23),"") -> 1 | I12: =IFERROR(IF(OR(NOT(ISNUMBER(H12)),NOT(ISNUMBER(S12))),"",S12+H12),"") -> 6 | J12: =IFERROR(IF(OR(I12="",Inputs!$C$19=""),"",Inputs!$C$19+ROUNDUP(I12*Inputs!$C$25,0)-1),"") | K12: AAOS integration | L12: Vehicle reads, lifecycle, permissions and mapping A use the same shared rules. | N12: =IFERROR(MIN(Inputs!$C$6,Inputs!$C$17)*Inputs!$C$29,"") -> 24 | O12: =IFERROR(MIN(Inputs!$C$7,Inputs!$C$16,F12)*Inputs!$C$28,"") -> 28 | P12: =IFERROR(MIN(Inputs!$C$7,Inputs!$C$16)*Inputs!$C$28,"") -> 28 | Q12: =IFERROR(N12+P12,"") -> 52 | R12: =IFERROR(IF(OR(Inputs!$C$32<>"OK",T12<>"OK"),"",MAX(E12,C12*Inputs!$C$24/O12,(C12+D12)*Inputs!$C$24/Q12)),"") -> 1 | S12: =IFERROR(IF(OR(Inputs!$C$32<>"OK",T12<>"OK",I11=""),"",I11+G12),"") -> 5 | T12: =IFERROR(IF(OR(COUNT(C12:G12)<>5,C12<0,D12<0,E12<0,F12<1,F12<>INT(F12),G12<0),"BLOCKED","OK"),"BLOCKED") -> OK
A13: P5 | B13: Demo first backend path | C13: 56 | D13: 36 | E13: 1 | F13: 2 | G13: 0 | H13: =IFERROR(IF(NOT(ISNUMBER(R13)),"",ROUNDUP(R13/Inputs!$C$23,0)*Inputs!$C$23),"") -> 2 | I13: =IFERROR(IF(OR(NOT(ISNUMBER(H13)),NOT(ISNUMBER(S13))),"",S13+H13),"") -> 8 | J13: =IFERROR(IF(OR(I13="",Inputs!$C$19=""),"",Inputs!$C$19+ROUNDUP(I13*Inputs!$C$25,0)-1),"") | K13: Reduced demo | L13: Mapping A -> shared rules -> MQTT/TLS -> receiver receipt. Remote settings stay off. | N13: =IFERROR(MIN(Inputs!$C$6,Inputs!$C$17)*Inputs!$C$29,"") -> 24 | O13: =IFERROR(MIN(Inputs!$C$7,Inputs!$C$16,F13)*Inputs!$C$28,"") -> 28 | P13: =IFERROR(MIN(Inputs!$C$7,Inputs!$C$16)*Inputs!$C$28,"") -> 28 | Q13: =IFERROR(N13+P13,"") -> 52 | R13: =IFERROR(IF(OR(Inputs!$C$32<>"OK",T13<>"OK"),"",MAX(E13,C13*Inputs!$C$24/O13,(C13+D13)*Inputs!$C$24/Q13)),"") -> 2 | S13: =IFERROR(IF(OR(Inputs!$C$32<>"OK",T13<>"OK",I12=""),"",I12+G13),"") -> 6 | T13: =IFERROR(IF(OR(COUNT(C13:G13)<>5,C13<0,D13<0,E13<0,F13<1,F13<>INT(F13),G13<0),"BLOCKED","OK"),"BLOCKED") -> OK
A14: P6 | B14: Test replacement connection | C14: 56 | D14: 40 | E14: 1 | F14: 2 | G14: 0 | H14: =IFERROR(IF(NOT(ISNUMBER(R14)),"",ROUNDUP(R14/Inputs!$C$23,0)*Inputs!$C$23),"") -> 2 | I14: =IFERROR(IF(OR(NOT(ISNUMBER(H14)),NOT(ISNUMBER(S14))),"",S14+H14),"") -> 10 | J14: =IFERROR(IF(OR(I14="",Inputs!$C$19=""),"",Inputs!$C$19+ROUNDUP(I14*Inputs!$C$25,0)-1),"") | K14: S3 | L14: S3: MQTT/HTTPS keep report meaning, IDs, decisions and equivalent receiver confirmation. | N14: =IFERROR(MIN(Inputs!$C$6,Inputs!$C$17)*Inputs!$C$29,"") -> 24 | O14: =IFERROR(MIN(Inputs!$C$7,Inputs!$C$16,F14)*Inputs!$C$28,"") -> 28 | P14: =IFERROR(MIN(Inputs!$C$7,Inputs!$C$16)*Inputs!$C$28,"") -> 28 | Q14: =IFERROR(N14+P14,"") -> 52 | R14: =IFERROR(IF(OR(Inputs!$C$32<>"OK",T14<>"OK"),"",MAX(E14,C14*Inputs!$C$24/O14,(C14+D14)*Inputs!$C$24/Q14)),"") -> 2 | S14: =IFERROR(IF(OR(Inputs!$C$32<>"OK",T14<>"OK",I13=""),"",I13+G14),"") -> 8 | T14: =IFERROR(IF(OR(COUNT(C14:G14)<>5,C14<0,D14<0,E14<0,F14<1,F14<>INT(F14),G14<0),"BLOCKED","OK"),"BLOCKED") -> OK
A15: P7 | B15: Test outage and restart | C15: 84 | D15: 56 | E15: 2 | F15: 2 | G15: 0 | H15: =IFERROR(IF(NOT(ISNUMBER(R15)),"",ROUNDUP(R15/Inputs!$C$23,0)*Inputs!$C$23),"") -> 3 | I15: =IFERROR(IF(OR(NOT(ISNUMBER(H15)),NOT(ISNUMBER(S15))),"",S15+H15),"") -> 13 | J15: =IFERROR(IF(OR(I15="",Inputs!$C$19=""),"",Inputs!$C$19+ROUNDUP(I15*Inputs!$C$25,0)-1),"") | K15: S4 | L15: S4: bounded restart-safe queue, retries, expiry and visible losses/duplicates. | N15: =IFERROR(MIN(Inputs!$C$6,Inputs!$C$17)*Inputs!$C$29,"") -> 24 | O15: =IFERROR(MIN(Inputs!$C$7,Inputs!$C$16,F15)*Inputs!$C$28,"") -> 28 | P15: =IFERROR(MIN(Inputs!$C$7,Inputs!$C$16)*Inputs!$C$28,"") -> 28 | Q15: =IFERROR(N15+P15,"") -> 52 | R15: =IFERROR(IF(OR(Inputs!$C$32<>"OK",T15<>"OK"),"",MAX(E15,C15*Inputs!$C$24/O15,(C15+D15)*Inputs!$C$24/Q15)),"") -> 3 | S15: =IFERROR(IF(OR(Inputs!$C$32<>"OK",T15<>"OK",I14=""),"",I14+G15),"") -> 10 | T15: =IFERROR(IF(OR(COUNT(C15:G15)<>5,C15<0,D15<0,E15<0,F15<1,F15<>INT(F15),G15<0),"BLOCKED","OK"),"BLOCKED") -> OK
A16: P8 | B16: Protect reporting settings | C16: 48 | D16: 30 | E16: 1 | F16: 1 | G16: 0 | H16: =IFERROR(IF(NOT(ISNUMBER(R16)),"",ROUNDUP(R16/Inputs!$C$23,0)*Inputs!$C$23),"") -> 2 | I16: =IFERROR(IF(OR(NOT(ISNUMBER(H16)),NOT(ISNUMBER(S16))),"",S16+H16),"") -> 15 | J16: =IFERROR(IF(OR(I16="",Inputs!$C$19=""),"",Inputs!$C$19+ROUNDUP(I16*Inputs!$C$25,0)-1),"") | K16: S5 | L16: S5: only authorized reporting changes; reject bad/replayed input and vehicle-control requests. | N16: =IFERROR(MIN(Inputs!$C$6,Inputs!$C$17)*Inputs!$C$29,"") -> 24 | O16: =IFERROR(MIN(Inputs!$C$7,Inputs!$C$16,F16)*Inputs!$C$28,"") -> 28 | P16: =IFERROR(MIN(Inputs!$C$7,Inputs!$C$16)*Inputs!$C$28,"") -> 28 | Q16: =IFERROR(N16+P16,"") -> 52 | R16: =IFERROR(IF(OR(Inputs!$C$32<>"OK",T16<>"OK"),"",MAX(E16,C16*Inputs!$C$24/O16,(C16+D16)*Inputs!$C$24/Q16)),"") -> 1.7142857 | S16: =IFERROR(IF(OR(Inputs!$C$32<>"OK",T16<>"OK",I15=""),"",I15+G16),"") -> 13 | T16: =IFERROR(IF(OR(COUNT(C16:G16)<>5,C16<0,D16<0,E16<0,F16<1,F16<>INT(F16),G16<0),"BLOCKED","OK"),"BLOCKED") -> OK
A17: P9 | B17: Validate reuse and hand over | C17: 64 | D17: 70 | E17: 2 | F17: 2 | G17: 0 | H17: =IFERROR(IF(NOT(ISNUMBER(R17)),"",ROUNDUP(R17/Inputs!$C$23,0)*Inputs!$C$23),"") -> 3 | I17: =IFERROR(IF(OR(NOT(ISNUMBER(H17)),NOT(ISNUMBER(S17))),"",S17+H17),"") -> 18 | J17: =IFERROR(IF(OR(I17="",Inputs!$C$19=""),"",Inputs!$C$19+ROUNDUP(I17*Inputs!$C$25,0)-1),"") | K17: Gate C / D-Design | L17: S1-S6 across A/B and both paths; fixed baseline, runbook and substantiated next-platform design. | N17: =IFERROR(MIN(Inputs!$C$6,Inputs!$C$17)*Inputs!$C$29,"") -> 24 | O17: =IFERROR(MIN(Inputs!$C$7,Inputs!$C$16,F17)*Inputs!$C$28,"") -> 28 | P17: =IFERROR(MIN(Inputs!$C$7,Inputs!$C$16)*Inputs!$C$28,"") -> 28 | Q17: =IFERROR(N17+P17,"") -> 52 | R17: =IFERROR(IF(OR(Inputs!$C$32<>"OK",T17<>"OK"),"",MAX(E17,C17*Inputs!$C$24/O17,(C17+D17)*Inputs!$C$24/Q17)),"") -> 2.5769231 | S17: =IFERROR(IF(OR(Inputs!$C$32<>"OK",T17<>"OK",I16=""),"",I16+G17),"") -> 15 | T17: =IFERROR(IF(OR(COUNT(C17:G17)<>5,C17<0,D17<0,E17<0,F17<1,F17<>INT(F17),G17<0),"BLOCKED","OK"),"BLOCKED") -> OK
B20: BASE TOTAL | C20: =IFERROR(SUM(C9:C17),"") -> 476 | D20: =IFERROR(SUM(D9:D17),"") -> 352 | G20: =IFERROR(SUM(G9:G17),"") -> 0 | H20: =IFERROR(SUM(H9:H17),"") -> 18 | I20: =IFERROR(IF(OR(Inputs!C32<>"OK",COUNT(I9:I17)<>9),"",I17),"") -> 18 | J20: =IFERROR(IF(OR(I20="",Inputs!$C$19=""),"",Inputs!$C$19+ROUNDUP(I20*Inputs!$C$25,0)-1),"")
A22: Work is not the same as staffed time. Default estimates total 828 accepted-work hours; nominal staffing includes mentoring, learning, coordination and capacity that cannot always be used on the critical path.
A25: Phase duration = round up the largest of: minimum weeks, expert-only work / expert lead capacity, or all work / combined capacity. Waits are then added. Expert capacity can cover support work without being counted twice.
A28: Forecast is not a test result. The target design is separate from an actual AAOS SDV runtime port. Production use and independent assurance are not included.

Sheet Scenarios
A1: Compare teams | same pilot scope
A3: The scope and work estimates stay the same. Scenarios use all other current Inputs and Plan assumptions.
A5: The first row follows Inputs. Other rows are editable examples, not staffing recommendations. A larger junior team can increase the senior mentoring load and delay expert-critical work.
A8: Scenario | B8: Experienced | C8: Junior | D8: Total | E8: Demo week | F8: Full pilot week | G8: With reserve week | H8: Nominal allocated hours | I8: Interpretation
A9: Current inputs | B9: =IFERROR(Inputs!C7,"") -> 1 | C9: =IFERROR(Inputs!C6,"") -> 1 | D9: =IFERROR(B9+C9,"") -> 2 | E9: =IFERROR(IF(J9<>"OK","",SUM(O9:S9)+SUM(Plan!$G$9:$G$13)),"") -> 8 | F9: =IFERROR(IF(J9<>"OK","",SUM(O9:W9)+SUM(Plan!$G$9:$G$17)),"") -> 18 | G9: =IFERROR(IF(F9="","",F9+Inputs!$C$22),"") -> 20 | H9: =IFERROR(IF(F9="","",F9*Inputs!$C$8*(B9*Inputs!$C$9+C9*Inputs!$C$10)),"") -> 1440 | I9: Live forecast for the selected team. | J9: =IFERROR(IF(OR(Inputs!$C$32<>"OK",B9<1,B9<>INT(B9),C9<0,C9<>INT(C9),K9<=0,COUNTIF(Plan!$T$9:$T$17,"BLOCKED")>0),"BLOCKED","OK"),"BLOCKED") -> OK | K9: =IFERROR(MAX(0,B9*Inputs!$C$8*Inputs!$C$9*Inputs!$C$12-C9*Inputs!$C$10*Inputs!$C$15),"") -> 28 | L9: =IFERROR(IF(B9>0,K9/B9,0),"") -> 28 | M9: =IFERROR(MIN(C9,Inputs!$C$17)*Inputs!$C$29,"") -> 24 | N9: =IFERROR(MIN(C9,Inputs!$C$17)*Inputs!$C$30,"") -> 12 | O9: =IFERROR(IF(J9<>"OK","",ROUNDUP(MAX(Plan!$E$9,Plan!$C$9*Inputs!$C$24/(MIN(B9,Inputs!$C$16,Plan!$F$9)*L9),(Plan!$C$9+Plan!$D$9)*Inputs!$C$24/(MIN(B9,Inputs!$C$16)*L9+N9))/Inputs!$C$23,0)*Inputs!$C$23),"") -> 2 | P9: =IFERROR(IF(J9<>"OK","",ROUNDUP(MAX(Plan!$E$10,Plan!$C$10*Inputs!$C$24/(MIN(B9,Inputs!$C$16,Plan!$F$10)*L9),(Plan!$C$10+Plan!$D$10)*Inputs!$C$24/(MIN(B9,Inputs!$C$16)*L9+M9))/Inputs!$C$23,0)*Inputs!$C$23),"") -> 2 | Q9: =IFERROR(IF(J9<>"OK","",ROUNDUP(MAX(Plan!$E$11,Plan!$C$11*Inputs!$C$24/(MIN(B9,Inputs!$C$16,Plan!$F$11)*L9),(Plan!$C$11+Plan!$D$11)*Inputs!$C$24/(MIN(B9,Inputs!$C$16)*L9+M9))/Inputs!$C$23,0)*Inputs!$C$23),"") -> 1 | R9: =IFERROR(IF(J9<>"OK","",ROUNDUP(MAX(Plan!$E$12,Plan!$C$12*Inputs!$C$24/(MIN(B9,Inputs!$C$16,Plan!$F$12)*L9),(Plan!$C$12+Plan!$D$12)*Inputs!$C$24/(MIN(B9,Inputs!$C$16)*L9+M9))/Inputs!$C$23,0)*Inputs!$C$23),"") -> 1 | S9: =IFERROR(IF(J9<>"OK","",ROUNDUP(MAX(Plan!$E$13,Plan!$C$13*Inputs!$C$24/(MIN(B9,Inputs!$C$16,Plan!$F$13)*L9),(Plan!$C$13+Plan!$D$13)*Inputs!$C$24/(MIN(B9,Inputs!$C$16)*L9+M9))/Inputs!$C$23,0)*Inputs!$C$23),"") -> 2 | T9: =IFERROR(IF(J9<>"OK","",ROUNDUP(MAX(Plan!$E$14,Plan!$C$14*Inputs!$C$24/(MIN(B9,Inputs!$C$16,Plan!$F$14)*L9),(Plan!$C$14+Plan!$D$14)*Inputs!$C$24/(MIN(B9,Inputs!$C$16)*L9+M9))/Inputs!$C$23,0)*Inputs!$C$23),"") -> 2 | U9: =IFERROR(IF(J9<>"OK","",ROUNDUP(MAX(Plan!$E$15,Plan!$C$15*Inputs!$C$24/(MIN(B9,Inputs!$C$16,Plan!$F$15)*L9),(Plan!$C$15+Plan!$D$15)*Inputs!$C$24/(MIN(B9,Inputs!$C$16)*L9+M9))/Inputs!$C$23,0)*Inputs!$C$23),"") -> 3 | V9: =IFERROR(IF(J9<>"OK","",ROUNDUP(MAX(Plan!$E$16,Plan!$C$16*Inputs!$C$24/(MIN(B9,Inputs!$C$16,Plan!$F$16)*L9),(Plan!$C$16+Plan!$D$16)*Inputs!$C$24/(MIN(B9,Inputs!$C$16)*L9+M9))/Inputs!$C$23,0)*Inputs!$C$23),"") -> 2 | W9: =IFERROR(IF(J9<>"OK","",ROUNDUP(MAX(Plan!$E$17,Plan!$C$17*Inputs!$C$24/(MIN(B9,Inputs!$C$16,Plan!$F$17)*L9),(Plan!$C$17+Plan!$D$17)*Inputs!$C$24/(MIN(B9,Inputs!$C$16)*L9+M9))/Inputs!$C$23,0)*Inputs!$C$23),"") -> 3
A10: =IFERROR(D10&" developers","") -> 2 developers | B10: 1 | C10: 1 | D10: =IFERROR(B10+C10,"") -> 2 | E10: =IFERROR(IF(J10<>"OK","",SUM(O10:S10)+SUM(Plan!$G$9:$G$13)),"") -> 8 | F10: =IFERROR(IF(J10<>"OK","",SUM(O10:W10)+SUM(Plan!$G$9:$G$17)),"") -> 18 | G10: =IFERROR(IF(F10="","",F10+Inputs!$C$22),"") -> 20 | H10: =IFERROR(IF(F10="","",F10*Inputs!$C$8*(B10*Inputs!$C$9+C10*Inputs!$C$10)),"") -> 1440 | I10: Editable comparison; role mix is shown in columns B-C. | J10: =IFERROR(IF(OR(Inputs!$C$32<>"OK",B10<1,B10<>INT(B10),C10<0,C10<>INT(C10),K10<=0,COUNTIF(Plan!$T$9:$T$17,"BLOCKED")>0),"BLOCKED","OK"),"BLOCKED") -> OK | K10: =IFERROR(MAX(0,B10*Inputs!$C$8*Inputs!$C$9*Inputs!$C$12-C10*Inputs!$C$10*Inputs!$C$15),"") -> 28 | L10: =IFERROR(IF(B10>0,K10/B10,0),"") -> 28 | M10: =IFERROR(MIN(C10,Inputs!$C$17)*Inputs!$C$29,"") -> 24 | N10: =IFERROR(MIN(C10,Inputs!$C$17)*Inputs!$C$30,"") -> 12 | O10: =IFERROR(IF(J10<>"OK","",ROUNDUP(MAX(Plan!$E$9,Plan!$C$9*Inputs!$C$24/(MIN(B10,Inputs!$C$16,Plan!$F$9)*L10),(Plan!$C$9+Plan!$D$9)*Inputs!$C$24/(MIN(B10,Inputs!$C$16)*L10+N10))/Inputs!$C$23,0)*Inputs!$C$23),"") -> 2 | P10: =IFERROR(IF(J10<>"OK","",ROUNDUP(MAX(Plan!$E$10,Plan!$C$10*Inputs!$C$24/(MIN(B10,Inputs!$C$16,Plan!$F$10)*L10),(Plan!$C$10+Plan!$D$10)*Inputs!$C$24/(MIN(B10,Inputs!$C$16)*L10+M10))/Inputs!$C$23,0)*Inputs!$C$23),"") -> 2 | Q10: =IFERROR(IF(J10<>"OK","",ROUNDUP(MAX(Plan!$E$11,Plan!$C$11*Inputs!$C$24/(MIN(B10,Inputs!$C$16,Plan!$F$11)*L10),(Plan!$C$11+Plan!$D$11)*Inputs!$C$24/(MIN(B10,Inputs!$C$16)*L10+M10))/Inputs!$C$23,0)*Inputs!$C$23),"") -> 1 | R10: =IFERROR(IF(J10<>"OK","",ROUNDUP(MAX(Plan!$E$12,Plan!$C$12*Inputs!$C$24/(MIN(B10,Inputs!$C$16,Plan!$F$12)*L10),(Plan!$C$12+Plan!$D$12)*Inputs!$C$24/(MIN(B10,Inputs!$C$16)*L10+M10))/Inputs!$C$23,0)*Inputs!$C$23),"") -> 1 | S10: =IFERROR(IF(J10<>"OK","",ROUNDUP(MAX(Plan!$E$13,Plan!$C$13*Inputs!$C$24/(MIN(B10,Inputs!$C$16,Plan!$F$13)*L10),(Plan!$C$13+Plan!$D$13)*Inputs!$C$24/(MIN(B10,Inputs!$C$16)*L10+M10))/Inputs!$C$23,0)*Inputs!$C$23),"") -> 2 | T10: =IFERROR(IF(J10<>"OK","",ROUNDUP(MAX(Plan!$E$14,Plan!$C$14*Inputs!$C$24/(MIN(B10,Inputs!$C$16,Plan!$F$14)*L10),(Plan!$C$14+Plan!$D$14)*Inputs!$C$24/(MIN(B10,Inputs!$C$16)*L10+M10))/Inputs!$C$23,0)*Inputs!$C$23),"") -> 2 | U10: =IFERROR(IF(J10<>"OK","",ROUNDUP(MAX(Plan!$E$15,Plan!$C$15*Inputs!$C$24/(MIN(B10,Inputs!$C$16,Plan!$F$15)*L10),(Plan!$C$15+Plan!$D$15)*Inputs!$C$24/(MIN(B10,Inputs!$C$16)*L10+M10))/Inputs!$C$23,0)*Inputs!$C$23),"") -> 3 | V10: =IFERROR(IF(J10<>"OK","",ROUNDUP(MAX(Plan!$E$16,Plan!$C$16*Inputs!$C$24/(MIN(B10,Inputs!$C$16,Plan!$F$16)*L10),(Plan!$C$16+Plan!$D$16)*Inputs!$C$24/(MIN(B10,Inputs!$C$16)*L10+M10))/Inputs!$C$23,0)*Inputs!$C$23),"") -> 2 | W10: =IFERROR(IF(J10<>"OK","",ROUNDUP(MAX(Plan!$E$17,Plan!$C$17*Inputs!$C$24/(MIN(B10,Inputs!$C$16,Plan!$F$17)*L10),(Plan!$C$17+Plan!$D$17)*Inputs!$C$24/(MIN(B10,Inputs!$C$16)*L10+M10))/Inputs!$C$23,0)*Inputs!$C$23),"") -> 3
A11: =IFERROR(D11&" developers","") -> 3 developers | B11: 2 | C11: 1 | D11: =IFERROR(B11+C11,"") -> 3 | E11: =IFERROR(IF(J11<>"OK","",SUM(O11:S11)+SUM(Plan!$G$9:$G$13)),"") -> 7 | F11: =IFERROR(IF(J11<>"OK","",SUM(O11:W11)+SUM(Plan!$G$9:$G$17)),"") -> 14.5 | G11: =IFERROR(IF(F11="","",F11+Inputs!$C$22),"") -> 16.5 | H11: =IFERROR(IF(F11="","",F11*Inputs!$C$8*(B11*Inputs!$C$9+C11*Inputs!$C$10)),"") -> 1740 | I11: Expert lead capacity and support work both constrain the forecast. | J11: =IFERROR(IF(OR(Inputs!$C$32<>"OK",B11<1,B11<>INT(B11),C11<0,C11<>INT(C11),K11<=0,COUNTIF(Plan!$T$9:$T$17,"BLOCKED")>0),"BLOCKED","OK"),"BLOCKED") -> OK | K11: =IFERROR(MAX(0,B11*Inputs!$C$8*Inputs!$C$9*Inputs!$C$12-C11*Inputs!$C$10*Inputs!$C$15),"") -> 62 | L11: =IFERROR(IF(B11>0,K11/B11,0),"") -> 31 | M11: =IFERROR(MIN(C11,Inputs!$C$17)*Inputs!$C$29,"") -> 24 | N11: =IFERROR(MIN(C11,Inputs!$C$17)*Inputs!$C$30,"") -> 12 | O11: =IFERROR(IF(J11<>"OK","",ROUNDUP(MAX(Plan!$E$9,Plan!$C$9*Inputs!$C$24/(MIN(B11,Inputs!$C$16,Plan!$F$9)*L11),(Plan!$C$9+Plan!$D$9)*Inputs!$C$24/(MIN(B11,Inputs!$C$16)*L11+N11))/Inputs!$C$23,0)*Inputs!$C$23),"") -> 2 | P11: =IFERROR(IF(J11<>"OK","",ROUNDUP(MAX(Plan!$E$10,Plan!$C$10*Inputs!$C$24/(MIN(B11,Inputs!$C$16,Plan!$F$10)*L11),(Plan!$C$10+Plan!$D$10)*Inputs!$C$24/(MIN(B11,Inputs!$C$16)*L11+M11))/Inputs!$C$23,0)*Inputs!$C$23),"") -> 1.5 | Q11: =IFERROR(IF(J11<>"OK","",ROUNDUP(MAX(Plan!$E$11,Plan!$C$11*Inputs!$C$24/(MIN(B11,Inputs!$C$16,Plan!$F$11)*L11),(Plan!$C$11+Plan!$D$11)*Inputs!$C$24/(MIN(B11,Inputs!$C$16)*L11+M11))/Inputs!$C$23,0)*Inputs!$C$23),"") -> 1 | R11: =IFERROR(IF(J11<>"OK","",ROUNDUP(MAX(Plan!$E$12,Plan!$C$12*Inputs!$C$24/(MIN(B11,Inputs!$C$16,Plan!$F$12)*L11),(Plan!$C$12+Plan!$D$12)*Inputs!$C$24/(MIN(B11,Inputs!$C$16)*L11+M11))/Inputs!$C$23,0)*Inputs!$C$23),"") -> 1 | S11: =IFERROR(IF(J11<>"OK","",ROUNDUP(MAX(Plan!$E$13,Plan!$C$13*Inputs!$C$24/(MIN(B11,Inputs!$C$16,Plan!$F$13)*L11),(Plan!$C$13+Plan!$D$13)*Inputs!$C$24/(MIN(B11,Inputs!$C$16)*L11+M11))/Inputs!$C$23,0)*Inputs!$C$23),"") -> 1.5 | T11: =IFERROR(IF(J11<>"OK","",ROUNDUP(MAX(Plan!$E$14,Plan!$C$14*Inputs!$C$24/(MIN(B11,Inputs!$C$16,Plan!$F$14)*L11),(Plan!$C$14+Plan!$D$14)*Inputs!$C$24/(MIN(B11,Inputs!$C$16)*L11+M11))/Inputs!$C$23,0)*Inputs!$C$23),"") -> 1.5 | U11: =IFERROR(IF(J11<>"OK","",ROUNDUP(MAX(Plan!$E$15,Plan!$C$15*Inputs!$C$24/(MIN(B11,Inputs!$C$16,Plan!$F$15)*L11),(Plan!$C$15+Plan!$D$15)*Inputs!$C$24/(MIN(B11,Inputs!$C$16)*L11+M11))/Inputs!$C$23,0)*Inputs!$C$23),"") -> 2 | V11: =IFERROR(IF(J11<>"OK","",ROUNDUP(MAX(Plan!$E$16,Plan!$C$16*Inputs!$C$24/(MIN(B11,Inputs!$C$16,Plan!$F$16)*L11),(Plan!$C$16+Plan!$D$16)*Inputs!$C$24/(MIN(B11,Inputs!$C$16)*L11+M11))/Inputs!$C$23,0)*Inputs!$C$23),"") -> 2 | W11: =IFERROR(IF(J11<>"OK","",ROUNDUP(MAX(Plan!$E$17,Plan!$C$17*Inputs!$C$24/(MIN(B11,Inputs!$C$16,Plan!$F$17)*L11),(Plan!$C$17+Plan!$D$17)*Inputs!$C$24/(MIN(B11,Inputs!$C$16)*L11+M11))/Inputs!$C$23,0)*Inputs!$C$23),"") -> 2
A12: =IFERROR(D12&" developers","") -> 4 developers | B12: 3 | C12: 1 | D12: =IFERROR(B12+C12,"") -> 4 | E12: =IFERROR(IF(J12<>"OK","",SUM(O12:S12)+SUM(Plan!$G$9:$G$13)),"") -> 7 | F12: =IFERROR(IF(J12<>"OK","",SUM(O12:W12)+SUM(Plan!$G$9:$G$17)),"") -> 14 | G12: =IFERROR(IF(F12="","",F12+Inputs!$C$22),"") -> 16 | H12: =IFERROR(IF(F12="","",F12*Inputs!$C$8*(B12*Inputs!$C$9+C12*Inputs!$C$10)),"") -> 2240 | I12: Phase caps and gate time limit further acceleration. | J12: =IFERROR(IF(OR(Inputs!$C$32<>"OK",B12<1,B12<>INT(B12),C12<0,C12<>INT(C12),K12<=0,COUNTIF(Plan!$T$9:$T$17,"BLOCKED")>0),"BLOCKED","OK"),"BLOCKED") -> OK | K12: =IFERROR(MAX(0,B12*Inputs!$C$8*Inputs!$C$9*Inputs!$C$12-C12*Inputs!$C$10*Inputs!$C$15),"") -> 96 | L12: =IFERROR(IF(B12>0,K12/B12,0),"") -> 32 | M12: =IFERROR(MIN(C12,Inputs!$C$17)*Inputs!$C$29,"") -> 24 | N12: =IFERROR(MIN(C12,Inputs!$C$17)*Inputs!$C$30,"") -> 12 | O12: =IFERROR(IF(J12<>"OK","",ROUNDUP(MAX(Plan!$E$9,Plan!$C$9*Inputs!$C$24/(MIN(B12,Inputs!$C$16,Plan!$F$9)*L12),(Plan!$C$9+Plan!$D$9)*Inputs!$C$24/(MIN(B12,Inputs!$C$16)*L12+N12))/Inputs!$C$23,0)*Inputs!$C$23),"") -> 2 | P12: =IFERROR(IF(J12<>"OK","",ROUNDUP(MAX(Plan!$E$10,Plan!$C$10*Inputs!$C$24/(MIN(B12,Inputs!$C$16,Plan!$F$10)*L12),(Plan!$C$10+Plan!$D$10)*Inputs!$C$24/(MIN(B12,Inputs!$C$16)*L12+M12))/Inputs!$C$23,0)*Inputs!$C$23),"") -> 1.5 | Q12: =IFERROR(IF(J12<>"OK","",ROUNDUP(MAX(Plan!$E$11,Plan!$C$11*Inputs!$C$24/(MIN(B12,Inputs!$C$16,Plan!$F$11)*L12),(Plan!$C$11+Plan!$D$11)*Inputs!$C$24/(MIN(B12,Inputs!$C$16)*L12+M12))/Inputs!$C$23,0)*Inputs!$C$23),"") -> 1 | R12: =IFERROR(IF(J12<>"OK","",ROUNDUP(MAX(Plan!$E$12,Plan!$C$12*Inputs!$C$24/(MIN(B12,Inputs!$C$16,Plan!$F$12)*L12),(Plan!$C$12+Plan!$D$12)*Inputs!$C$24/(MIN(B12,Inputs!$C$16)*L12+M12))/Inputs!$C$23,0)*Inputs!$C$23),"") -> 1 | S12: =IFERROR(IF(J12<>"OK","",ROUNDUP(MAX(Plan!$E$13,Plan!$C$13*Inputs!$C$24/(MIN(B12,Inputs!$C$16,Plan!$F$13)*L12),(Plan!$C$13+Plan!$D$13)*Inputs!$C$24/(MIN(B12,Inputs!$C$16)*L12+M12))/Inputs!$C$23,0)*Inputs!$C$23),"") -> 1.5 | T12: =IFERROR(IF(J12<>"OK","",ROUNDUP(MAX(Plan!$E$14,Plan!$C$14*Inputs!$C$24/(MIN(B12,Inputs!$C$16,Plan!$F$14)*L12),(Plan!$C$14+Plan!$D$14)*Inputs!$C$24/(MIN(B12,Inputs!$C$16)*L12+M12))/Inputs!$C$23,0)*Inputs!$C$23),"") -> 1.5 | U12: =IFERROR(IF(J12<>"OK","",ROUNDUP(MAX(Plan!$E$15,Plan!$C$15*Inputs!$C$24/(MIN(B12,Inputs!$C$16,Plan!$F$15)*L12),(Plan!$C$15+Plan!$D$15)*Inputs!$C$24/(MIN(B12,Inputs!$C$16)*L12+M12))/Inputs!$C$23,0)*Inputs!$C$23),"") -> 2 | V12: =IFERROR(IF(J12<>"OK","",ROUNDUP(MAX(Plan!$E$16,Plan!$C$16*Inputs!$C$24/(MIN(B12,Inputs!$C$16,Plan!$F$16)*L12),(Plan!$C$16+Plan!$D$16)*Inputs!$C$24/(MIN(B12,Inputs!$C$16)*L12+M12))/Inputs!$C$23,0)*Inputs!$C$23),"") -> 1.5 | W12: =IFERROR(IF(J12<>"OK","",ROUNDUP(MAX(Plan!$E$17,Plan!$C$17*Inputs!$C$24/(MIN(B12,Inputs!$C$16,Plan!$F$17)*L12),(Plan!$C$17+Plan!$D$17)*Inputs!$C$24/(MIN(B12,Inputs!$C$16)*L12+M12))/Inputs!$C$23,0)*Inputs!$C$23),"") -> 2
A13: =IFERROR(D13&" developers","") -> 2 developers | B13: 2 | C13: 0 | D13: =IFERROR(B13+C13,"") -> 2 | E13: =IFERROR(IF(J13<>"OK","",SUM(O13:S13)+SUM(Plan!$G$9:$G$13)),"") -> 7.5 | F13: =IFERROR(IF(J13<>"OK","",SUM(O13:W13)+SUM(Plan!$G$9:$G$17)),"") -> 15 | G13: =IFERROR(IF(F13="","",F13+Inputs!$C$22),"") -> 17 | H13: =IFERROR(IF(F13="","",F13*Inputs!$C$8*(B13*Inputs!$C$9+C13*Inputs!$C$10)),"") -> 1200 | I13: Experienced staff also cover the support workload. | J13: =IFERROR(IF(OR(Inputs!$C$32<>"OK",B13<1,B13<>INT(B13),C13<0,C13<>INT(C13),K13<=0,COUNTIF(Plan!$T$9:$T$17,"BLOCKED")>0),"BLOCKED","OK"),"BLOCKED") -> OK | K13: =IFERROR(MAX(0,B13*Inputs!$C$8*Inputs!$C$9*Inputs!$C$12-C13*Inputs!$C$10*Inputs!$C$15),"") -> 68 | L13: =IFERROR(IF(B13>0,K13/B13,0),"") -> 34 | M13: =IFERROR(MIN(C13,Inputs!$C$17)*Inputs!$C$29,"") -> 0 | N13: =IFERROR(MIN(C13,Inputs!$C$17)*Inputs!$C$30,"") -> 0 | O13: =IFERROR(IF(J13<>"OK","",ROUNDUP(MAX(Plan!$E$9,Plan!$C$9*Inputs!$C$24/(MIN(B13,Inputs!$C$16,Plan!$F$9)*L13),(Plan!$C$9+Plan!$D$9)*Inputs!$C$24/(MIN(B13,Inputs!$C$16)*L13+N13))/Inputs!$C$23,0)*Inputs!$C$23),"") -> 2 | P13: =IFERROR(IF(J13<>"OK","",ROUNDUP(MAX(Plan!$E$10,Plan!$C$10*Inputs!$C$24/(MIN(B13,Inputs!$C$16,Plan!$F$10)*L13),(Plan!$C$10+Plan!$D$10)*Inputs!$C$24/(MIN(B13,Inputs!$C$16)*L13+M13))/Inputs!$C$23,0)*Inputs!$C$23),"") -> 2 | Q13: =IFERROR(IF(J13<>"OK","",ROUNDUP(MAX(Plan!$E$11,Plan!$C$11*Inputs!$C$24/(MIN(B13,Inputs!$C$16,Plan!$F$11)*L13),(Plan!$C$11+Plan!$D$11)*Inputs!$C$24/(MIN(B13,Inputs!$C$16)*L13+M13))/Inputs!$C$23,0)*Inputs!$C$23),"") -> 1 | R13: =IFERROR(IF(J13<>"OK","",ROUNDUP(MAX(Plan!$E$12,Plan!$C$12*Inputs!$C$24/(MIN(B13,Inputs!$C$16,Plan!$F$12)*L13),(Plan!$C$12+Plan!$D$12)*Inputs!$C$24/(MIN(B13,Inputs!$C$16)*L13+M13))/Inputs!$C$23,0)*Inputs!$C$23),"") -> 1 | S13: =IFERROR(IF(J13<>"OK","",ROUNDUP(MAX(Plan!$E$13,Plan!$C$13*Inputs!$C$24/(MIN(B13,Inputs!$C$16,Plan!$F$13)*L13),(Plan!$C$13+Plan!$D$13)*Inputs!$C$24/(MIN(B13,Inputs!$C$16)*L13+M13))/Inputs!$C$23,0)*Inputs!$C$23),"") -> 1.5 | T13: =IFERROR(IF(J13<>"OK","",ROUNDUP(MAX(Plan!$E$14,Plan!$C$14*Inputs!$C$24/(MIN(B13,Inputs!$C$16,Plan!$F$14)*L13),(Plan!$C$14+Plan!$D$14)*Inputs!$C$24/(MIN(B13,Inputs!$C$16)*L13+M13))/Inputs!$C$23,0)*Inputs!$C$23),"") -> 1.5 | U13: =IFERROR(IF(J13<>"OK","",ROUNDUP(MAX(Plan!$E$15,Plan!$C$15*Inputs!$C$24/(MIN(B13,Inputs!$C$16,Plan!$F$15)*L13),(Plan!$C$15+Plan!$D$15)*Inputs!$C$24/(MIN(B13,Inputs!$C$16)*L13+M13))/Inputs!$C$23,0)*Inputs!$C$23),"") -> 2.5 | V13: =IFERROR(IF(J13<>"OK","",ROUNDUP(MAX(Plan!$E$16,Plan!$C$16*Inputs!$C$24/(MIN(B13,Inputs!$C$16,Plan!$F$16)*L13),(Plan!$C$16+Plan!$D$16)*Inputs!$C$24/(MIN(B13,Inputs!$C$16)*L13+M13))/Inputs!$C$23,0)*Inputs!$C$23),"") -> 1.5 | W13: =IFERROR(IF(J13<>"OK","",ROUNDUP(MAX(Plan!$E$17,Plan!$C$17*Inputs!$C$24/(MIN(B13,Inputs!$C$16,Plan!$F$17)*L13),(Plan!$C$17+Plan!$D$17)*Inputs!$C$24/(MIN(B13,Inputs!$C$16)*L13+M13))/Inputs!$C$23,0)*Inputs!$C$23),"") -> 2
A14: =IFERROR(D14&" developers","") -> 3 developers | B14: 1 | C14: 2 | D14: =IFERROR(B14+C14,"") -> 3 | E14: =IFERROR(IF(J14<>"OK","",SUM(O14:S14)+SUM(Plan!$G$9:$G$13)),"") -> 12 | F14: =IFERROR(IF(J14<>"OK","",SUM(O14:W14)+SUM(Plan!$G$9:$G$17)),"") -> 24.5 | G14: =IFERROR(IF(F14="","",F14+Inputs!$C$22),"") -> 26.5 | H14: =IFERROR(IF(F14="","",F14*Inputs!$C$8*(B14*Inputs!$C$9+C14*Inputs!$C$10)),"") -> 2940 | I14: More juniors may slow expert-critical work under the stated mentoring assumptions. | J14: =IFERROR(IF(OR(Inputs!$C$32<>"OK",B14<1,B14<>INT(B14),C14<0,C14<>INT(C14),K14<=0,COUNTIF(Plan!$T$9:$T$17,"BLOCKED")>0),"BLOCKED","OK"),"BLOCKED") -> OK | K14: =IFERROR(MAX(0,B14*Inputs!$C$8*Inputs!$C$9*Inputs!$C$12-C14*Inputs!$C$10*Inputs!$C$15),"") -> 22 | L14: =IFERROR(IF(B14>0,K14/B14,0),"") -> 22 | M14: =IFERROR(MIN(C14,Inputs!$C$17)*Inputs!$C$29,"") -> 48 | N14: =IFERROR(MIN(C14,Inputs!$C$17)*Inputs!$C$30,"") -> 24 | O14: =IFERROR(IF(J14<>"OK","",ROUNDUP(MAX(Plan!$E$9,Plan!$C$9*Inputs!$C$24/(MIN(B14,Inputs!$C$16,Plan!$F$9)*L14),(Plan!$C$9+Plan!$D$9)*Inputs!$C$24/(MIN(B14,Inputs!$C$16)*L14+N14))/Inputs!$C$23,0)*Inputs!$C$23),"") -> 3 | P14: =IFERROR(IF(J14<>"OK","",ROUNDUP(MAX(Plan!$E$10,Plan!$C$10*Inputs!$C$24/(MIN(B14,Inputs!$C$16,Plan!$F$10)*L14),(Plan!$C$10+Plan!$D$10)*Inputs!$C$24/(MIN(B14,Inputs!$C$16)*L14+M14))/Inputs!$C$23,0)*Inputs!$C$23),"") -> 3 | Q14: =IFERROR(IF(J14<>"OK","",ROUNDUP(MAX(Plan!$E$11,Plan!$C$11*Inputs!$C$24/(MIN(B14,Inputs!$C$16,Plan!$F$11)*L14),(Plan!$C$11+Plan!$D$11)*Inputs!$C$24/(MIN(B14,Inputs!$C$16)*L14+M14))/Inputs!$C$23,0)*Inputs!$C$23),"") -> 1.5 | R14: =IFERROR(IF(J14<>"OK","",ROUNDUP(MAX(Plan!$E$12,Plan!$C$12*Inputs!$C$24/(MIN(B14,Inputs!$C$16,Plan!$F$12)*L14),(Plan!$C$12+Plan!$D$12)*Inputs!$C$24/(MIN(B14,Inputs!$C$16)*L14+M14))/Inputs!$C$23,0)*Inputs!$C$23),"") -> 1.5 | S14: =IFERROR(IF(J14<>"OK","",ROUNDUP(MAX(Plan!$E$13,Plan!$C$13*Inputs!$C$24/(MIN(B14,Inputs!$C$16,Plan!$F$13)*L14),(Plan!$C$13+Plan!$D$13)*Inputs!$C$24/(MIN(B14,Inputs!$C$16)*L14+M14))/Inputs!$C$23,0)*Inputs!$C$23),"") -> 3 | T14: =IFERROR(IF(J14<>"OK","",ROUNDUP(MAX(Plan!$E$14,Plan!$C$14*Inputs!$C$24/(MIN(B14,Inputs!$C$16,Plan!$F$14)*L14),(Plan!$C$14+Plan!$D$14)*Inputs!$C$24/(MIN(B14,Inputs!$C$16)*L14+M14))/Inputs!$C$23,0)*Inputs!$C$23),"") -> 3 | U14: =IFERROR(IF(J14<>"OK","",ROUNDUP(MAX(Plan!$E$15,Plan!$C$15*Inputs!$C$24/(MIN(B14,Inputs!$C$16,Plan!$F$15)*L14),(Plan!$C$15+Plan!$D$15)*Inputs!$C$24/(MIN(B14,Inputs!$C$16)*L14+M14))/Inputs!$C$23,0)*Inputs!$C$23),"") -> 4 | V14: =IFERROR(IF(J14<>"OK","",ROUNDUP(MAX(Plan!$E$16,Plan!$C$16*Inputs!$C$24/(MIN(B14,Inputs!$C$16,Plan!$F$16)*L14),(Plan!$C$16+Plan!$D$16)*Inputs!$C$24/(MIN(B14,Inputs!$C$16)*L14+M14))/Inputs!$C$23,0)*Inputs!$C$23),"") -> 2.5 | W14: =IFERROR(IF(J14<>"OK","",ROUNDUP(MAX(Plan!$E$17,Plan!$C$17*Inputs!$C$24/(MIN(B14,Inputs!$C$16,Plan!$F$17)*L14),(Plan!$C$17+Plan!$D$17)*Inputs!$C$24/(MIN(B14,Inputs!$C$16)*L14+M14))/Inputs!$C$23,0)*Inputs!$C$23),"") -> 3
A17: HOW TO READ THE COMPARISON
A18: A staffing comparison, not a hiring recommendation. Additional people do not remove test gates or prove business value. All experienced contributors must have the required skills.
A21: To model 2 -> 3 developers in the active plan: set Inputs!C5 to 3 and leave Inputs!C6 at 1. To add a junior instead, set both total developers and junior count. Review the role mix, not only the total.
A24: The model applies one team from the planning start. It does not model mid-project joining dates or actual progress. For an in-flight reforecast, save a baseline copy and review remaining work and capacity with the senior lead.

Sheet Business Case
A1: Business case | cost and value
A3: Optional inputs. Blank means not quantified, not free. Costs and savings are forecasts, not approval or realized results.
A4: 1 FUNDING ENVELOPE - ENTER APPROVED RATES AND COST ASSUMPTIONS
A5: Currency / unit | E5: Use the same currency for every monetary input. No automatic currency conversion.
A6: Experienced cost / allocated hour | E6: Fully loaded internal rate or agreed billing rate. Include the cost basis.
A7: Junior cost / allocated hour | E7: Enter 0 only if no juniors are allocated; otherwise use the approved rate.
A8: Recovery non-labour cap | E8: Includes recovery infrastructure, access or authorized outside support. Enter 0 explicitly if none.
A9: Full-pilot non-labour cap | E9: Includes the recovery non-labour amount; do not add recovery twice.
A10: Reserve non-labour cap | E10: Additional cost only if reserve is released. It is not automatically authorized.
A11: Budget input check | C11: =IFERROR(IF(OR(C5="",COUNT(C6:C10)<>5),"NOT SET",IF(OR(C6<=0,C7<0,AND(Inputs!C6>0,C7<=0),MIN(C8:C10)<0,C9<C8),"INVALID","SET")),"INVALID") -> NOT SET | E11: Not SET? Complete or correct the blue fields; schedule calculations remain independent.
A12: Allocated labour cost / week | C12: =IFERROR(IF(OR(C11<>"SET",Inputs!C32<>"OK"),"",Inputs!C8*(Inputs!C7*Inputs!C9*C6+Inputs!C6*Inputs!C10*C7)),"") | E12: Uses all allocated hours, including mentoring/support; not just accepted-work capacity.
A14: CALCULATED COST - CURRENT TEAM AND FORECAST
A16: Recovery phase | C16: =IFERROR(IF(OR(NOT(ISNUMBER(C12)),Plan!I20=""),"",Plan!I9*C12+C8),"") | E16: The immediate approval tranche, including any pre-phase waits entered in Plan.
A17: Full pilot, excluding reserve | C17: =IFERROR(IF(OR(NOT(ISNUMBER(C12)),Plan!I20=""),"",Plan!I17*C12+C9),"") | E17: Includes recovery. Assumes the team remains allocated through all phases and waits.
A18: Additional reserve | C18: =IFERROR(IF(OR(NOT(ISNUMBER(C12)),Plan!I20=""),"",Inputs!C22*C12+C10),"") | E18: Only for sponsor-approved delays or acceptance defects; not additional features.
A19: Maximum planning envelope | C19: =IFERROR(IF(COUNT(C17:C18)<>2,"",SUM(C17:C18)),"") | E19: Full pilot plus reserve. This is a planning ceiling, not a purchase authorization.
A21: Cost forecasts assume constant rates and the selected team from the planning start. No hidden implementer is included. Any external review or equipment must be priced explicitly. Monetary payback is not calculated from unpriced effort savings.
A24: 2 REUSE VALUE - COMPARABLE EFFORT, SAME SCOPE AND QUALITY
A25: One later integration without reuse (h) | E25: Include implementation, review, integration and tests for the agreed scope.
A26: One later integration with reuse (h) | E26: Use the same accounting and quality obligations as the no-reuse baseline.
A27: Extra one-time reuse investment (h) | E27: Only the incremental work versus the one-off approach; not all project hours.
A28: Additional maintenance in period (h) | E28: Total added maintenance across the defined comparison period, not per integration.
A29: Expected later integrations (count) | E29: Whole number, excluding the initial pilot. This is an assumption about adoption.
A30: Evidence / comparison period | E30: Record source estimates or measured work, scope, period and reviewer. Never label forecasts as realized savings.
A31: Value input check | C31: =IFERROR(IF(OR(COUNT(C25:C29)<>5,C30=""),"NOT QUANTIFIED",IF(OR(C25<=0,MIN(C26:C29)<0,C29<>INT(C29)),"INVALID","SET")),"INVALID") -> NOT QUANTIFIED | E31: Complete all inputs and the evidence/period note before using the value forecast.
A33: Time saved per later integration (h) | C33: =IFERROR(IF(C31<>"SET","",C25-C26),"") | E33: A zero/negative result gives no positive effort-saving case.
A34: Break-even later integrations | C34: =IFERROR(IF(C31<>"SET","",IF(C33<=0,"NO PAYBACK",ROUNDUP((C27+C28)/C33,0))),"") | E34: Includes extra setup and maintenance. Assumes the same saving for each later integration.
A35: Forecast net effort saved (h) | C35: =IFERROR(IF(C31<>"SET","",C29*C33-C27-C28),"") | E35: Positive = fewer hours under these assumptions. Negative = extra effort; neither is realized cash.
A37: Illustration only (not the live inputs): 80 h without reuse; 40 h with reuse; 160 h extra setup; 40 h added maintenance. Break-even is 5 later integrations. The pilot itself does not prove those values. Compare like-for-like effort; do not mix delivery-capacity hours with nominal staffed hours.
A41: Source: prior DAR and dynamic plan for scope/capacity; user-entered rates and comparable effort for cost/value. New business-case formulas are proposed management checks, not measured outcomes. Use SDV_Vehicle_Status_Approval_Report_EN.md / .docx for the approval narrative.

Sheet Guide
A1: Read me | model and sources
A3: The workbook is the single source for changing resources, forecast dates and the management report.
A5: USE THE WORKBOOK
A6: Change the team | B6: Inputs!C5 = total developers; C6 = juniors. Experienced count is calculated. Example: 3 total and 1 junior means 2 experienced developers.
A8: Review capacity | B8: Check allocation, accepted-work rates and mentoring. Defaults reproduce the v1.0 assumptions: 28 experienced hours/week; junior 12 in recovery and 24 after recovery.
A10: Review forecast | B10: Report shows milestones, schedule variance and allocated hours. Plan shows phase calculations. Scenarios compares role mixes without changing the active plan.
A12: Edit the estimate | B12: Plan blue cells change work, minimum duration, critical lead slots and waits. Inputs!C24 applies one work multiplier. Save a baseline copy before changing estimates.
A14: Share the report | B14: Use Report with the companion approval report. Excel updates without macros. Word/Markdown explain the stable idea, examples, risks and approval criteria; they are not rewritten when inputs change.
A17: WHAT THE MODEL DOES
A18: Capacity | B18: Experienced pool = people x paid hours x allocation x usable-time rate minus allocated-junior mentoring. Split mentoring evenly across the experienced pool.
A20: Work assignment | B20: Expert-only work cannot be delegated to juniors. Support work may be done by juniors or spare experienced capacity; total work is counted once.
A22: Duration | B22: For each phase, take MAX(minimum weeks, expert work / expert critical capacity, all work / combined capacity). Multiply work by the estimate factor and round up to the selected step.
A24: Sequence and waits | B24: Phases are sequential. Roles may work together within a phase. Waiting weeks are added before that phase; the team is assumed allocated through waits and reserve.
A26: Scope and limits | B26: No automatic initiative switch or test pass. No holiday calendar, individual join dates, actual-progress tracking, overtime or independent assurance. Leave start blank until agreed. Review parallel-work assumptions for larger teams.
A29: TRACEABILITY AND APPROVAL
A30: Planning source [P1] | B30: SDV_Telematics_Vehicle_Status_AAOS_First_Plan_Revision_EN.md: AAOS-first baseline, core separation, mapping/cloud substitutions, S1-S6 and claim limits.
A32: Resource source [P2] | B32: SDV_Vehicle_Status_DAR_EN_v1_0_One_Senior_One_Junior.md: sections 20 and 20B supply the capacity assumptions and 476 expert / 352 junior-work hours. Sections 2A-3A supply the Automotive alternatives.
A34: Model additions | B34: Phase W5-W6 split equally for the Gate B checkpoint. Junior work becomes a shared-work pool. Phase floors, contributor caps, rounding, scenario staffing and wait controls are editable modeling assumptions, not measured facts.
A36: Baseline reconciliation | B36: The original workload is preserved: 476 expert-only + 352 support hours. Default forecasts remain recovery W2, core W5, demo W8, full pilot W18 and reserve W20. Dates now remain blank until a start is entered.
A38: Approvals still needed | B38: Sponsor confirms objective, people, start, capacity and funding. Senior validates workload, skills, semantics, security and gate evidence. Re-estimate after recovery; record accepted deviations.
A41: OPTIONAL BUSINESS CASE AND APPROVAL
A42: Budget | B42: Business Case C5:C10: enter currency, rates and non-labour caps. Recovery cost appears in Report. Full cost includes recovery once; reserve is separate. Blank inputs mean not quantified.
A44: Practical value | B44: Business Case C25:C30: enter comparable hours, incremental setup, period maintenance, expected future integrations and evidence. Break-even and net effort are forecasts, not cash savings or measured adoption.
A46: Save the approval | B46: Sponsor records the selected team, allocation, recovery cap, start and Gate A conditions. Save the approved workbook snapshot. Changing resources recalculates a proposal; it does not grant approval.
A48: Prior short DAR [P3] | B48: SDV_Vehicle_Status_DAR_Short_EN.md and SDV_Vehicle_Status_Plan.xlsx (v1.1): prior scope, six test groups and dynamic forecast. The current approval report adds management examples and an optional cost/value model.
